aind_metadata_validator/__init__.py
aind_metadata_validator/core_validator.py
aind_metadata_validator/field_validator.py
aind_metadata_validator/mappings.py
aind_metadata_validator/metadata_validator.py
aind_metadata_validator/sync.py
aind_metadata_validator/utils.py
aind_metadata_validator-0.11.5.dist-info/licenses/LICENSE
aind_metadata_validator-0.11.5.dist-info/METADATA
aind_metadata_validator-0.11.5.dist-info/WHEEL
aind_metadata_validator-0.11.5.dist-info/top_level.txt
aind_metadata_validator-0.11.5.dist-info/RECORD
